MANIFEST.in
README.md
pyproject.toml
requirements.txt
setup.py
acts.core.egg-info/PKG-INFO
acts.core.egg-info/SOURCES.txt
acts.core.egg-info/dependency_links.txt
acts.core.egg-info/requires.txt
acts.core.egg-info/top_level.txt
acts/core/__init__.py
acts/core/logging.py
acts/core/version.py
acts/core/dataset/__init__.py
acts/core/dataset/osm.py
acts/core/dataset/survey.py
acts/core/dataset/parquets/__init__.py
acts/core/dataset/parquets/quezon-city.parquet
acts/core/model/__init__.py
acts/core/model/base.py
acts/core/model/util.py
acts/core/util/__init__.py
acts/core/util/generic_util.py
requirements/base.txt
requirements/dev.txt