Metadata-Version: 2.1
Name: acts.core
Version: 0.4.0
Summary: ACTS Core is the Core Backend Python Library for Project ACTS.
Author: Project ACTS - Software Development Team
License: UNKNOWN
Platform: UNKNOWN
Requires-Python: >=3.7
